copilot/__init__.py
copilot/__main__.py
copilot/authflow.py
copilot_import-1.0.0.dist-info/entry_points.txt
copilot_import-1.0.0.dist-info/LICENSE
copilot_import-1.0.0.dist-info/WHEEL
copilot_import-1.0.0.dist-info/METADATA
copilot_import-1.0.0.dist-info/RECORD
