Metadata-Version: 2.1
Name: copilot-import
Version: 1.0.0
Summary: Inspired by https://github.com/drathier/stack-overflow-import
Home-page: https://github.com/MythicManiac/copilot-import
License: MIT
Author: Mythic
Author-email: mythicmaniac@gmail.com
Requires-Python: >=3.8,<4.0
Classifier: License :: OSI Approved :: MIT License
Classifier: Programming Language :: Python :: 3
Classifier: Programming Language :: Python :: 3.8
Classifier: Programming Language :: Python :: 3.9
Requires-Dist: requests (>=2.26.0,<3.0.0)
Project-URL: Repository, https://github.com/MythicManiac/copilot-import
